vendor/templeEX/original/registerfile.v
`timescale 1ns / 1ns
module registerfile #(
    parameter N = 16,
    M = 5
) (
    input clk,
    en,
    input [N-1:0] wr_data,
    input [M-1:0] addr,
    output [N-1:0] rd_data
);

  reg [N-1:0] mem[(2**M)-1:0];

  assign rd_data = (addr == 29) ? 0 : ( (addr == 30) ? 16'h1 : ( (addr == 31) ? 16'hffff : mem[addr]));

  always @(posedge clk) begin
    if (en) begin
      mem[addr] <= wr_data;
    end
  end

endmodule

vendor/templeEX/original/alu.v
`timescale 1ns / 1ns
module alu #(
    parameter DATA_WIDTH = 16
) (
    input [DATA_WIDTH-1:0] data_in1,
    data_in2,
    input [1:0] op,
    output reg [DATA_WIDTH-1:0] data_out,
    output [2:0] flag
);

  reg carry;
  wire zero, neg;
  wire [16:0] data_in1_add, data_in2_add;

  assign data_in1_add = data_in1;
  assign data_in2_add = data_in2;

  always @(*) begin
    case (op)
      2'b00: {carry, data_out} = {1'b0, ~(data_in1 | data_in2)};
      2'b01: {carry, data_out} = data_in1_add + data_in2_add;
      2'b10: {carry, data_out} = {1'b0, data_in1};
      2'b11: {carry, data_out} = {1'b0, (data_in2 >> 1)};
    endcase
  end

  assign zero = ~(|data_out);
  assign neg  = data_out[DATA_WIDTH-1];

  assign flag = {zero, neg, carry};

endmodule

vendor/templeEX/original/register.v
`timescale 1ns / 1ns
module register #(
    parameter N = 16
) (
    input clk,
    rst,
    en,
    input [N-1:0] data_in,
    output reg [N-1:0] data_out
);

  always @(posedge clk, negedge rst) begin
    if (!rst) begin
      data_out <= 0;
    end else begin
      if (en) begin
        data_out <= data_in;
      end
    end
  end
endmodule

vendor/templeEX/original/head.v
`timescale 1ns / 1ns

`define FETCH 4'b0000
`define NOR 4'b0001
`define ADD 4'b0010
`define LD 4'b0011
`define SD 4'b0100
`define SETI1 4'b0101
`define SETI2 4'b0110
`define SRL 4'b0111
`define JL1 4'b1000
`define JL2 4'b1001
`define PC 4'b1010
`define MOVE 4'b1011

vendor/templeEX/original/decode.v
`timescale 1ns / 1ns

`include "head.v"

module decode (
    input [2:0] op,
    input [3:0] state,
    output reg [13:0] dec
);

  //  {pc_sel,addr_sel,reg_sel,acc_sel,imm_sel[1:0],alu_op[1:0],pc_en,acc_en,regfile_en,rf_en,flag_en,en}

  always @(*) begin
    case (state)
      `FETCH: begin
        if (op == 3'b110) begin
          dec = 14'b1_1_x_x_xx_xx_1_0_0_1_0_0;
        end else if (op == 3'b101) begin
          dec = 14'b1_1_x_x_xx_xx_1_0_0_0_0_0;
        end else if (op == 3'b011) begin
          dec = 14'bx_1_0_x_1x_xx_0_0_1_0_0_0;
        end else begin
          dec = 14'bx_1_x_x_xx_xx_0_0_0_1_0_0;
        end
      end
      `NOR: dec = 14'bx_x_x_1_xx_00_0_1_0_0_1_0;
      `ADD: dec = 14'bx_x_x_1_xx_01_0_1_0_0_1_0;
      `LD: dec = 14'bx_0_x_0_1x_xx_0_1_0_0_0_0;
      `SD: dec = 14'bx_0_x_x_xx_xx_0_0_0_0_0_1;
      `SETI1: dec = 14'b1_1_x_0_00_xx_1_1_0_0_0_0;
      `SETI2: dec = 14'b1_1_x_0_01_xx_0_1_0_0_0_0;
      `JL1: dec = 14'bx_1_1_x_xx_xx_0_0_1_0_0_0;
      `JL2: dec = 14'b0_x_x_x_xx_xx_1_0_0_0_0_0;
      `SRL: dec = 14'bx_x_x_1_xx_11_0_1_0_0_1_0;
      `MOVE: dec = 14'bx_1_0_x_xx_xx_0_0_0_0_0_1;
      `PC: dec = 14'b1_x_x_x_xx_xx_1_0_0_0_0_0;
    endcase
  end
endmodule

vendor/templeEX/original/state.v
`timescale 1ns / 1ns

`include "head.v"

module state (
    input            clk,
    rst,
    input      [2:0] op,
    output reg [3:0] state,
    input      [2:0] flag
);
  reg [3:0] nextstate;
  reg       br;


  always @(*) begin
    case (state)
      `FETCH: begin
        if (op == 3'b000) begin
          nextstate = `NOR;
        end else if (op == 3'b001) begin
          nextstate = `ADD;
        end else if (op == 3'b010) begin
          nextstate = `LD;
        end else if (op == 3'b011) begin
          nextstate = `PC;
        end else if (op == 3'b100) begin
          nextstate = `SD;
        end else if (op == 3'b101) begin
          nextstate = `SETI1;
        end else if (op == 3'b110) begin
          nextstate = `JL1;
        end else nextstate = `SRL;
      end
      `NOR: begin
        nextstate = `PC;
      end
      `ADD: nextstate = `PC;
      `LD: nextstate = `PC;
      `SD: nextstate = `PC;
      `SETI1: nextstate = `SETI2;
      `SETI2: nextstate = `PC;
      `SRL: nextstate = `PC;
      `JL1:
      if (br) nextstate = `JL2;
      else nextstate = `PC;
      `JL2: nextstate = `FETCH;
      //`MOVE: nextstate = `PC;
      `PC: nextstate = `FETCH;
      default: nextstate = `FETCH;
    endcase  // case (state)
  end

  always @(posedge clk, negedge rst) begin
    if (!rst) begin
      state <= `FETCH;
    end else begin
      state <= nextstate;
    end
  end

  always @(*) begin
    case (op)
      3'h0: br = 0;
      3'h1: br = flag[0];
      3'h2: br = flag[1];
      3'h3: br = flag[1] | flag[0];
      3'h4: br = flag[2];
      3'h5: br = flag[2] | flag[0];
      3'h6: br = flag[2] | flag[1];
      3'h7: br = 1;
      default: br = 0;
    endcase  // case (cond)
  end  // always @ begin


endmodule  // state

vendor/templeEX/original/temple.v
`timescale 1ns / 1ns
module Temple #(
    parameter ADDR_WIDTH = 16,
    parameter DATA_WIDTH = 16
) (
    input                   clk,
    rst,
    output [ADDR_WIDTH-1:0] addr,
    input  [          15:0] rd_data,
    output [          15:0] wr_data,
    output                  en
);
  wire [15:0] pc_sel_data, acc_sel_data, reg_sel_data, imm_sel_data;
  wire [15:0] pc_out, add_out, acc_out;
  wire [15:0] regfile_out, rf_out, alu_out;

  wire [2:0] flag_out, alu_flag;


  wire pc_sel, acc_sel, reg_sel, addr_sel;
  wire pc_en, acc_en, regfile_en, flag_en, rf_en;
  wire [1:0] imm_sel, alu_op;

  wire [ 2:0] op;

  wire [ 3:0] state;

  wire [13:0] dec;

  wire [ 4:0] regfile_addr;

  wire [ 7:0] half_imm_data;



  assign {pc_sel,addr_sel,reg_sel,acc_sel,imm_sel[1:0],alu_op[1:0],pc_en,acc_en,regfile_en,rf_en,flag_en,en} = dec;

  state statemachine (
      .clk(clk),
      .rst(rst),
      .op(op),
      .state(state),
      .flag(flag_out)
  );
  decode decode (
      .op(op),
      .state(state),
      .dec(dec)
  );

  register PC (
      .clk(clk),
      .rst(rst),
      .en(pc_en),
      .data_in(pc_sel_data),
      .data_out(pc_out)
  );
  register Acc (
      .clk(clk),
      .rst(rst),
      .en(acc_en),
      .data_in(acc_sel_data),
      .data_out(acc_out)
  );
  register #(
      .N(3)
  ) flag (
      .clk(clk),
      .rst(rst),
      .en(flag_en),
      .data_in(alu_flag),
      .data_out(flag_out)
  );
  register regi (
      .clk(clk),
      .rst(rst),
      .en(rf_en),
      .data_in(regfile_out),
      .data_out(rf_out)
  );

  alu alu (
      .data_in1(rf_out),
      .data_in2(acc_out),
      .op(alu_op),
      .data_out(alu_out),
      .flag(alu_flag)
  );
  registerfile regfile (
      .clk(clk),
      .en(regfile_en),
      .wr_data(reg_sel_data),
      .rd_data(regfile_out),
      .addr(regfile_addr)
  );

  assign pc_sel_data = (pc_sel) ? add_out : rf_out;
  assign add_out = pc_out + 16'h1;
  assign acc_sel_data = (acc_sel) ? alu_out : imm_sel_data;
  assign reg_sel_data = (reg_sel) ? add_out : acc_out;
  assign addr = addr_sel ? {pc_out[15:1], 1'b0} : {rf_out[15:1], 1'b0};
  assign wr_data = acc_out;

  assign op = (pc_out[0]) ? rd_data[15:13] : rd_data[7:5];
  assign regfile_addr = (pc_out[0]) ? rd_data[12:8] : rd_data[4:0];
  assign half_imm_data = (pc_out[0]) ? rd_data[15:8] : rd_data[7:0];

  assign imm_sel_data = (imm_sel[1]) ? rd_data[15:0] : ( (imm_sel[0]) ? {half_imm_data, acc_out[7:0]} : {acc_out[15:8], half_imm_data});

endmodule  // Temple

vendor/templeEX/original/testfix.v
`timescale 1ns / 1ns

module testfix;
  reg         clk;
  reg         rst;
  wire [15:0] rd_data;
  wire [15:0] wr_data;
  wire [15:0] addr;
  wire        wen;

  integer i, F_HANDLE, num;


  parameter STEP = 100;
  always #(STEP / 2) begin
    clk = ~clk;
    i   = i + 1;
  end


  initial begin
    $dumpfile("testfix.vcd");  //GTKwaveで波形表示する為の記述
    $dumpvars(0, testfix);  //GTKwaveで波形表示する為の記述

    $readmemb("../programs/aaa1.dat", memory.mem);

    {memory.mem[1001], memory.mem[1000]} = 16'h9;
    {memory.mem[1003], memory.mem[1002]} = 16'h8;
    {memory.mem[1005], memory.mem[1004]} = 16'h7;
    {memory.mem[1007], memory.mem[1006]} = 16'h6;
    {memory.mem[1009], memory.mem[1008]} = 16'h5;
    {memory.mem[1011], memory.mem[1010]} = 16'h4;
    {memory.mem[1013], memory.mem[1012]} = 16'h3;
    {memory.mem[1015], memory.mem[1014]} = 16'h2;
    {memory.mem[1017], memory.mem[1016]} = 16'h1;
    {memory.mem[1019], memory.mem[1018]} = 16'h0;

    #(STEP * 0) clk = 0;
    rst = 1;
    i   = 0;
    #(STEP + 10) rst = 0;
    #(STEP * 2 + 10) rst = 1;


    while (temple.PC.data_out != 16'hFFFF) begin
      #STEP;
    end

    F_HANDLE = $fopen("dump.log");
    $fwrite(F_HANDLE, "cycle = %d\n", i);
    for (i = 1000; i < 1020; i = i + 2) begin
      $fwrite(F_HANDLE, "mem[%6d] = %d\n", i, $unsigned({memory.mem[i+1], memory.mem[i]}));
    end
    $finish;

  end  // initial begin



  Temple temple (
      .clk(clk),
      .rst(rst),
      .rd_data(rd_data),
      .addr(addr),
      .wr_data(wr_data),
      .en(wen)
  );

  memory memory (
      .clk(clk),
      .rw(wen),
      .addr(addr),
      .rdata(rd_data),
      .wdata(wr_data)
  );


endmodule

module memory (
    clk,
    rw,
    addr,
    rdata,
    wdata
);
  input rw, clk;
  input [15:0] addr;
  input [15:0] wdata;
  output [15:0] rdata;
  reg [7:0] mem[0:65535];


  assign rdata = (!rw) ? {mem[addr+1], mem[addr]} : 16'hz;  // Read mode

  always @(posedge clk) if (rw) {mem[addr+1], mem[addr]} = wdata;  // Write mode
endmodule

vendor/templeEX/original/testfix.vcd
$date
	Wed Jan 31 11:04:11 2024
$end
$version
	Icarus Verilog
$end
$timescale
	1ns
$end
$scope module testfix $end
$var wire 16 ! wr_data [15:0] $end
$var wire 1 " wen $end
$var wire 16 # rd_data [15:0] $end
$var wire 16 $ addr [15:0] $end
$var parameter 32 % STEP $end
$var reg 1 & clk $end
$var reg 1 ' rst $end
$var integer 32 ( F_HANDLE [31:0] $end
$var integer 32 ) i [31:0] $end
$scope module memory $end
$var wire 1 & clk $end
$var wire 16 * wdata [15:0] $end
$var wire 1 " rw $end
$var wire 16 + rdata [15:0] $end
$var wire 16 , addr [15:0] $end
$upscope $end
$scope module temple $end
$var wire 1 & clk $end
$var wire 16 - rd_data [15:0] $end
$var wire 1 ' rst $end
$var wire 16 . wr_data [15:0] $end
$var wire 4 / state [3:0] $end
$var wire 16 0 rf_out [15:0] $end
$var wire 1 1 rf_en $end
$var wire 16 2 regfile_out [15:0] $end
$var wire 1 3 regfile_en $end
$var wire 5 4 regfile_addr [4:0] $end
$var wire 16 5 reg_sel_data [15:0] $end
$var wire 1 6 reg_sel $end
$var wire 16 7 pc_sel_data [15:0] $end
$var wire 1 8 pc_sel $end
$var wire 16 9 pc_out [15:0] $end
$var wire 1 : pc_en $end
$var wire 3 ; op [2:0] $end
$var wire 16 < imm_sel_data [15:0] $end
$var wire 2 = imm_sel [1:0] $end
$var wire 8 > half_imm_data [7:0] $end
$var wire 3 ? flag_out [2:0] $end
$var wire 1 @ flag_en $end
$var wire 1 " en $end
$var wire 14 A dec [13:0] $end
$var wire 16 B alu_out [15:0] $end
$var wire 2 C alu_op [1:0] $end
$var wire 3 D alu_flag [2:0] $end
$var wire 1 E addr_sel $end
$var wire 16 F addr [15:0] $end
$var wire 16 G add_out [15:0] $end
$var wire 16 H acc_sel_data [15:0] $end
$var wire 1 I acc_sel $end
$var wire 16 J acc_out [15:0] $end
$var wire 1 K acc_en $end
$var parameter 32 L ADDR_WIDTH $end
$var parameter 32 M DATA_WIDTH $end
$scope module Acc $end
$var wire 1 & clk $end
$var wire 16 N data_in [15:0] $end
$var wire 1 K en $end
$var wire 1 ' rst $end
$var parameter 32 O N $end
$var reg 16 P data_out [15:0] $end
$upscope $end
$scope module PC $end
$var wire 1 & clk $end
$var wire 16 Q data_in [15:0] $end
$var wire 1 : en $end
$var wire 1 ' rst $end
$var parameter 32 R N $end
$var reg 16 S data_out [15:0] $end
$upscope $end
$scope module alu $end
$var wire 16 T data_in2 [15:0] $end
$var wire 2 U op [1:0] $end
$var wire 1 V zero $end
$var wire 1 W neg $end
$var wire 3 X flag [2:0] $end
$var wire 17 Y data_in2_add [16:0] $end
$var wire 17 Z data_in1_add [16:0] $end
$var wire 16 [ data_in1 [15:0] $end
$var parameter 32 \ DATA_WIDTH $end
$var reg 1 ] carry $end
$var reg 16 ^ data_out [15:0] $end
$upscope $end
$scope module decode $end
$var wire 3 _ op [2:0] $end
$var wire 4 ` state [3:0] $end
$var reg 14 a dec [13:0] $end
$upscope $end
$scope module flag $end
$var wire 1 & clk $end
$var wire 3 b data_in [2:0] $end
$var wire 1 @ en $end
$var wire 1 ' rst $end
$var parameter 32 c N $end
$var reg 3 d data_out [2:0] $end
$upscope $end
$scope module regfile $end
$var wire 5 e addr [4:0] $end
$var wire 1 & clk $end
$var wire 1 3 en $end
$var wire 16 f wr_data [15:0] $end
$var wire 16 g rd_data [15:0] $end
$var parameter 32 h M $end
$var parameter 32 i N $end
$upscope $end
$scope module regi $end
$var wire 1 & clk $end
$var wire 16 j data_in [15:0] $end
$var wire 1 1 en $end
$var wire 1 ' rst $end
$var parameter 32 k N $end
$var reg 16 l data_out [15:0] $end
$upscope $end
$scope module statemachine $end
$var wire 1 & clk $end
$var wire 3 m flag [2:0] $end
$var wire 3 n op [2:0] $end
$var wire 1 ' rst $end
$var reg 1 o br $end
$var reg 4 p nextstate [3:0] $end
$var reg 4 q state [3:0] $end
$upscope $end
$upscope $end
$upscope $end
$enddefinitions $end
$comment Show the parameter values. $end
$dumpall
b10000 k
b10000 i
b101 h
b11 c
b10000 \
b10000 R
b10000 O
b10000 M
b10000 L
b1100100 %
$end
#0
$dumpvars
bx q
bx p
xo
bx n
bx m
bx l
bx j
bx g
bx f
bx e
bx d
bx b
bx a
bx `
bx _
bx ^
x]
bx [
b0xxxxxxxxxxxxxxxx Z
b0xxxxxxxxxxxxxxxx Y
bx X
xW
xV
bx U
bx T
bx S
bx Q
bx P
bx N
xK
bx J
xI
bx H
bx G
bx0 F
xE
bx D
bx C
bx B
bx A
x@
bx ?
bx >
bx =
bx <
bx ;
x:
bx 9
x8
bx 7
x6
bx 5
bx 4
x3
bx 2
x1
bx 0
bx /
bx .
bx -
bx0 ,
bx +
bx *
b0 )
bx (
1'
0&
bx0 $
bx #
x"
bx !
$end
#50
b1 )
1&
#100
b10 )
0&
#110
18
bx0x00000x0x00000 <
b101 ;
b101 _
b101 n
b0 4
b0 e
b10100000 >
b10100000 #
b10100000 +
b10100000 -
b0 $
b0 ,
b0 F
1E
1:
0K
03
01
0@
0"
0o
b0x 5
b0x f
b1 7
b1 Q
b11xxxxxx100000 A
b11xxxxxx100000 a
b101 p
b0 Z
b0 0
b0 [
b0 l
b0 ?
b0 d
b0 m
b0 Y
b0 !
b0 *
b0 .
b0 J
b0 P
b0 T
b1 G
b0 9
b0 S
b0 /
b0 `
b0 q
0'
#150
b11 )
1&
#200
b100 )
0&
#250
b101 )
1&
#300
b110 )
0&
#320
1'
#350
b0 <
b0 H
b0 N
0I
b0 =
1K
b0 >
b0 ;
b0 _
b0 n
b11x000xx110000 A
b11x000xx110000 a
b110 p
b0x0 5
b0x0 f
b10 7
b10 Q
b101 /
b101 `
b101 q
b10 G
b1 9
b1 S
b111 )
1&
#400
b1000 )
0&
#450
b0 H
b0 N
b0 <
b110000000000000 #
b110000000000000 +
b110000000000000 -
b0 >
b0 ;
b0 _
b0 n
b10 $
b10 ,
b10 F
b1 =
0:
b0xx 5
b0xx f
b11 7
b11 Q
b11x001xx010000 A
b11x001xx010000 a
b1010 p
b11 G
b10 9
b10 S
b110 /
b110 `
b110 q
b1001 )
1&
#500
b1010 )
0&
#550
bx ;
bx _
bx n
bx 4
bx e
bx >
bx #
bx +
bx -
bx <
b0x0 $
b0x0 ,
b0x0 F
bx H
bx N
xE
xI
bx =
1:
0K
b1xxxxxxx100000 A
b1xxxxxxx100000 a
b0 p
b1010 /
b1010 `
b1010 q
b1011 )
1&
#600
b1100 )
0&
#650
06
b1x =
13
b110000000000000 <
b11 ;
b11 _
b11 n
b0 4
b0 e
b1100000 >
b110000000000000 #
b110000000000000 +
b110000000000000 -
b10 $
b10 ,
b10 F
x8
1E
0:
01
b0 5
b0 f
b0x00 7
b0x00 Q
bx10x1xxx001000 A
bx10x1xxx001000 a
b1010 p
b100 G
b11 9
b11 S
b0 /
b0 `
b0 q
b1101 )
1&
#700
b1110 )
0&
#750
bx ;
bx _
bx n
bx 4
bx e
bx >
bx #
bx +
bx -
bx <
bx 2
bx g
bx j
b100 7
b100 Q
b0x0 $
b0x0 ,
b0x0 F
b0x00 5
b0x00 f
18
xE
x6
bx =
1:
03
b1xxxxxxx100000 A
b1xxxxxxx100000 a
b0 p
b1010 /
b1010 `
b1010 q
b1111 )
1&
#800
b10000 )
0&
#850
06
b1x =
13
b1010000001100001 <
b11 ;
b11 _
b11 n
b1 4
b1 e
b1100001 >
b1010000001100001 #
b1010000001100001 +
b1010000001100001 -
b100 $
b100 ,
b100 F
x8
1E
0:
01
b0 5
b0 f
b0x0x 7
b0x0x Q
bx10x1xxx001000 A
bx10x1xxx001000 a
b1010 p
b101 G
b100 9
b100 S
b0 /
b0 `
b0 q
b10001 )
1&
#900
b10010 )
0&
#950
bx ;
bx _
bx n
bx 4
bx e
bx >
bx #
bx +
bx -
bx <
bx 2
bx g
bx j
b101 7
b101 Q
b0x00 $
b0x00 ,
b0x00 F
b0x0x 5
b0x0x f
18
xE
x6
bx =
1:
03
b1xxxxxxx100000 A
b1xxxxxxx100000 a
b0 p
b1010 /
b1010 `
b1010 q
b10011 )
1&
#1000
b10100 )
0&
#1050
bx0x00000xxx0000x <
b0 2
b0 g
b0 j
b101 ;
b101 _
b101 n
b0 4
b0 e
b10100000 >
b1010000001100001 #
b1010000001100001 +
b1010000001100001 -
b100 $
b100 ,
b100 F
18
1E
1:
01
b0xx0 5
b0xx0 f
b110 7
b110 Q
b11xxxxxx100000 A
b11xxxxxx100000 a
b101 p
b110 G
b101 9
b101 S
b0 /
b0 `
b0 q
b10101 )
1&
#1100
b10110 )
0&
#1150
bx 2
bx g
bx j
b1010 <
b1010 H
b1010 N
b1010 #
b1010 +
b1010 -
0I
b0 =
1K
b1010 >
b1010 4
b1010 e
b0 ;
b0 _
b0 n
b110 $
b110 ,
b110 F
b11x000xx110000 A
b11x000xx110000 a
b110 p
b0xxx 5
b0xxx f
b111 7
b111 Q
b101 /
b101 `
b101 q
b111 G
b110 9
b110 S
b10111 )
1&
#1200
b11000 )
0&
#1250
b0 2
b0 g
b0 j
b0 >
b0 4
b0 e
b1 =
0:
b10x0 5
b10x0 f
b1000 7
b1000 Q
b11x001xx010000 A
b11x001xx010000 a
b1010 p
b1010 Y
b1010 !
b1010 *
b1010 .
b1010 J
b1010 P
b1010 T
b1000 G
b111 9
b111 S
b110 /
b110 `
b110 q
b11001 )
1&
#1300
b11010 )
0&
#1350
bx 2
bx g
bx j
bx ;
bx _
bx n
bx 4
bx e
bx >
bx #
bx +
bx -
bx <
b0xx0 $
b0xx0 ,
b0xx0 F
bx H
bx N
xE
xI
bx =
1:
0K
b1xxxxxxx100000 A
b1xxxxxxx100000 a
b0 p
b1010 /
b1010 `
b1010 q
b11011 )
1&
#1400
b11100 )
0&
#1450
06
b1x =
13
b1001100010 <
b11 ;
b11 _
b11 n
b10 4
b10 e
b1100010 >
b1001100010 #
b1001100010 +
b1001100010 -
b1000 $
b1000 ,
b1000 F
x8
1E
0:
01
b1010 5
b1010 f
b0x00x 7
b0x00x Q
bx10x1xxx001000 A
bx10x1xxx001000 a
b1010 p
b1001 G
b1000 9
b1000 S
b0 /
b0 `
b0 q
b11101 )
1&
#1500
b11110 )
0&
#1550
bx ;
bx _
bx n
bx 4
bx e
bx >
bx #
bx +
bx -
bx <
bx 2
bx g
bx j
b1001 7
b1001 Q
b0x000 $
b0x000 ,
b0x000 F
b10xx 5
b10xx f
18
xE
x6
bx =
1:
03
b1xxxxxxx100000 A
b1xxxxxxx100000 a
b0 p
b1010 /
b1010 `
b1010 q
b11111 )
1&
#1600
b100000 )
0&
#1650
b0x00xx0x010 <
b1010 2
b1010 g
b1010 j
b0 ;
b0 _
b0 n
b10 4
b10 e
b10 >
b1001100010 #
b1001100010 +
b1001100010 -
b1000 $
b1000 ,
b1000 F
x8
1E
0:
11
b1010 5
b1010 f
b0x0x0 7
b0x0x0 Q
bx1xxxxxx000100 A
bx1xxxxxx000100 a
b1 p
b1010 G
b1001 9
b1001 S
b0 /
b0 `
b0 q
b100001 )
1&
#1700
b100010 )
0&
#1750
bx 2
bx g
bx j
bx ;
bx _
bx n
bx 4
bx e
bx >
bx <
bx #
bx +
bx -
0V
1W
b10x0 $
b10x0 ,
b10x0 F
b1111111111110101 H
b1111111111110101 N
b10 D
b10 X
b10 b
0]
b1111111111110101 B
b1111111111110101 ^
xE
1I
b0 C
b0 U
1K
01
1@
bx1xx00010010 A
bx1xx00010010 a
b1010 p
b1010 7
b1010 Q
b1 /
b1 `
b1 q
b1010 Z
b1010 0
b1010 [
b1010 l
b100011 )
1&
#1800
b100100 )
0&
#1850
1V
b100 D
b100 X
b100 b
0W
bx H
bx N
18
xI
bx C
bx U
1:
0K
0@
b0 B
b0 ^
bx 5
bx f
b1xxxxxxx100000 A
b1xxxxxxx100000 a
b0 p
b10 ?
b10 d
b10 m
b1111111111110101 Y
b1111111111110101 !
b1111111111110101 *
b1111111111110101 .
b1111111111110101 J
b1111111111110101 P
b1111111111110101 T
b1010 /
b1010 `
b1010 q
b100101 )
1&
#1900
b100110 )
0&
#1950
bx0x000000xx000xx H
bx0x000000xx000xx N
06
b1x =
13
b1010000001100011 <
1o
b11 ;
b11 _
b11 n
b11 4
b11 e
b1100011 >
b1010000001100011 #
b1010000001100011 +
b1010000001100011 -
x8
1E
0:
01
b1010 $
b1010 ,
b1010 F
bx10x1xxx001000 A
bx10x1xxx001000 a
b1010 p
b1111111111110101 5
b1111111111110101 f
b101x 7
b101x Q
b0 /
b0 `
b0 q
b1011 G
b1010 9
b1010 S
b100111 )
1&
#2000
b101000 )
0&
#2050
bx0xxx H
bx0xxx N
bx1xxxxxx11x0xx1 <
b1111111111110101 2
b1111111111110101 g
b1111111111110101 j
b1011 7
b1011 Q
bx1 5
bx1 f
18
xE
x6
bx =
1:
03
b1xxxxxxx100000 A
b1xxxxxxx100000 a
b0 p
b1010 /
b1010 `
b1010 q
b101001 )
1&
#2100
b101010 )
0&
#2150
bx0xxx H
bx0xxx N
b0 2
b0 g
b0 j
b1x1xxxxxxx1x0xxx <
0o
18
1E
x6
bx =
1:
03
b10100000 >
b0 4
b0 e
b101 ;
b101 _
b101 n
b11xxxxxx100000 A
b11xxxxxx100000 a
b101 p
bx10x 5
bx10x f
b1100 7
b1100 Q
b0 /
b0 `
b0 q
b1100 G
b1011 9
b1011 S
b101011 )
1&
#2200
b101100 )
0&
#2250
b0 2
b0 g
b0 j
b1111111100000001 <
0o
b1 #
b1 +
b1 -
b1111111100000001 H
b1111111100000001 N
b1 >
b1 4
b1 e
b0 ;
b0 _
b0 n
b1100 $
b1100 ,
b1100 F
0I
b0 =
1K
bx101 5
bx101 f
b1101 7
b1101 Q
b11x000xx110000 A
b11x000xx110000 a
b110 p
b1101 G
b1100 9
b1100 S
b101 /
b101 `
b101 q
b101101 )
1&
#2300
b101110 )
0&
#2350
b1 H
b1 N
b1 <
b1 =
0:
b0 >
b0 4
b0 e
b11x001xx010000 A
b11x001xx010000 a
b1010 p
b1110 7
b1110 Q
bx0000xxxx 5
bx0000xxxx f
b110 /
b110 `
b110 q
b1110 G
b1101 9
b1101 S
b1111111100000001 Y
b1111111100000001 !
b1111111100000001 *
b1111111100000001 .
b1111111100000001 J
b1111111100000001 P
b1111111100000001 T
b101111 )
1&
#2400
b110000 )
0&
#2450
bx 2
bx g
bx j
bx ;
bx _
bx n
bx 4
bx e
bx >
bx #
bx +
bx -
bx <
b1xx0 $
b1xx0 ,
b1xx0 F
bx H
bx N
xE
xI
bx =
1:
0K
b0xxxx 5
b0xxxx f
b1xxxxxxx100000 A
b1xxxxxxx100000 a
b0 p
b1 Y
b1 !
b1 *
b1 .
b1 J
b1 P
b1 T
b1010 /
b1010 `
b1010 q
b110001 )
1&
#2500
b110010 )
0&
#2550
b0x000xx00x000xx H
b0x000xx00x000xx N
b0x000xx00x000x1 <
b1111111111110101 2
b1111111111110101 g
b1111111111110101 j
b1 ;
b1 _
b1 n
b11 4
b11 e
b100011 >
b10000100100011 #
b10000100100011 +
b10000100100011 -
x8
1E
0:
11
b1110 $
b1110 ,
b1110 F
bx1xxxxxx000100 A
bx1xxxxxx000100 a
b10 p
b0xxx1 5
b0xxx1 f
b1x1x 7
b1x1x Q
b0 /
b0 `
b0 q
b1111 G
b1110 9
b1110 S
b110011 )
1&
#2600
b110100 )
0&
#2650
bx 2
bx g
bx j
bx ;
bx _
bx n
bx 4
bx e
bx >
bx <
bx #
bx +
bx -
0V
b10 D
b10 X
b10 b
1W
bx1x0 $
bx1x0 ,
bx1x0 F
b1111111111110110 H
b1111111111110110 N
b1111111111110110 B
b1111111111110110 ^
xE
1I
b1 C
b1 U
1K
01
1@
bx1x1 7
bx1x1 Q
bx1xx01010010 A
bx1xx01010010 a
b1010 p
b1111111111110101 Z
b1111111111110101 0
b1111111111110101 [
b1111111111110101 l
b10 /
b10 `
b10 q
b110101 )
1&
#2700
b110110 )
0&
#2750
b1111 7
b1111 Q
18
xI
bx C
bx U
1:
0K
0@
bx H
bx N
b1xxxxxxx100000 A
b1xxxxxxx100000 a
b0 p
b11 D
b11 X
b11 b
1]
b1111111111101011 B
b1111111111101011 ^
bx11x 5
bx11x f
b1010 /
b1010 `
b1010 q
b1111111111110110 Y
b1111111111110110 !
b1111111111110110 *
b1111111111110110 .
b1111111111110110 J
b1111111111110110 P
b1111111111110110 T
b110111 )
1&
#2800
b111000 )
0&
#2850
bx1xxxx1xx1xxxxx H
bx1xxxx1xx1xxxxx N
bx1xxxx1xx1x0xxx <
b0 2
b0 g
b0 j
b1 ;
b1 _
b1 n
b1 4
b1 e
b100001 >
b10000100100011 #
b10000100100011 +
b10000100100011 -
b1110 $
b1110 ,
b1110 F
x8
1E
0:
11
bx10xx0 5
bx10xx0 f
bx10x0x 7
bx10x0x Q
bx1xxxxxx000100 A
bx1xxxxxx000100 a
b10 p
b10000 G
b1111 9
b1111 S
b0 /
b0 `
b0 q
b111001 )
1&
#2900
b111010 )
0&
#2950
bx 2
bx g
bx j
bx ;
bx _
bx n
bx 4
bx e
bx >
bx <
bx #
bx +
bx -
b0xxx0 $
b0xxx0 ,
b0xxx0 F
b1111111111110110 H
b1111111111110110 N
b10 D
b10 X
b10 b
0]
b1111111111110110 B
b1111111111110110 ^
xE
1I
b1 C
b1 U
1K
01
1@
bx1xx01010010 A
bx1xx01010010 a
b1010 p
b0x0000 7
b0x0000 Q
b10 /
b10 `
b10 q
b0 Z
b0 0
b0 [
b0 l
b111011 )
1&
#3000
b111100 )
0&
#3050
b10000 7
b10000 Q
bx H
bx N
18
xI
bx C
bx U
1:
0K
0@
b1xxxxxxx100000 A
b1xxxxxxx100000 a
b0 p
b1010 /
b1010 `
b1010 q
b111101 )
1&
#3100
b111110 )
0&
#3150
bx1xxxxx1x1x0xx0 H
bx1xxxxx1x1x0xx0 N
bx1xxxxx1x1x0xx0 <
b0 2
b0 g
b0 j
b101 ;
b101 _
b101 n
b0 4
b0 e
b10100000 >
b11000010100000 #
b11000010100000 +
b11000010100000 -
18
1E
1:
01
b10000 $
b10000 ,
b10000 F
b11xxxxxx100000 A
b11xxxxxx100000 a
b101 p
bx10xxx 5
bx10xxx f
b10001 7
b10001 Q
b0 /
b0 `
b0 q
b10001 G
b10000 9
b10000 S
b111111 )
1&
#3200
b1000000 )
0&
#3250
bx 2
bx g
bx j
b1111111100110000 H
b1111111100110000 N
b1111111100110000 <
b110000 >
b10000 4
b10000 e
b1 ;
b1 _
b1 n
0I
b0 =
1K
bx10x10 5
bx10x10 f
b10010 7
b10010 Q
b11x000xx110000 A
b11x000xx110000 a
b110 p
b10010 G
b10001 9
b10001 S
b101 /
b101 `
b101 q
b1000001 )
1&
#3300
b1000010 )
0&
#3350
b110000 H
b110000 N
b0 2
b0 g
b0 j
b110000 <
b110010100000000 #
b110010100000000 +
b110010100000000 -
b1 =
0:
b0 >
b0 4
b0 e
b0 ;
b0 _
b0 n
b10010 $
b10010 ,
b10010 F
b11x001xx010000 A
b11x001xx010000 a
b1010 p
b10011 7
b10011 Q
bx00x100xx 5
bx00x100xx f
b110 /
b110 `
b110 q
b10011 G
b10010 9
b10010 S
b1111111100110000 Y
b1111111100110000 !
b1111111100110000 *
b1111111100110000 .
b1111111100110000 J
b1111111100110000 P
b1111111100110000 T
b1000011 )
1&
#3400
b1000100 )
0&
